djako_plugin_ya_metrics/__init__.py
djako_plugin_ya_metrics/admin.py
djako_plugin_ya_metrics/apps.py
djako_plugin_ya_metrics/models.py
djako_plugin_ya_metrics/tests.py
djako_plugin_ya_metrics/urls.py
djako_plugin_ya_metrics/views.py
djako_plugin_ya_metrics/migrations/0001_initial.py
djako_plugin_ya_metrics/migrations/0002_remove_yandexmetrikacounter_datefrom_and_more.py
djako_plugin_ya_metrics/migrations/0003_yandexmetrikawidgetstyle_and_more.py
djako_plugin_ya_metrics/migrations/0004_alter_yandexmetrikacounterwidget_options_and_more.py
djako_plugin_ya_metrics/migrations/0005_yandexmetrikawidgetstyle_chart_type.py
djako_plugin_ya_metrics/migrations/0006_yandexmetrikacounterwidget_hidden.py
djako_plugin_ya_metrics/migrations/__init__.py
djako_plugin_ya_metrics/static/css/admin_metrics.css
djako_plugin_ya_metrics/static/css/yandex_metrics.css
djako_plugin_ya_metrics/static/js/metrika.js
djako_plugin_ya_metrics/static/js/yandex_metrics.js
djako_plugin_ya_metrics/static/js/ChartJS/chart.min.js
djako_plugin_ya_metrics/static/js/jQuery/jquery.min.js
djako_plugin_ya_metrics/templates/admin/djako_yandex_metrics/widgets.html
djako_plugin_ya_metrics/templates/admin/yandex_metrika/widgets.html
djako_plugin_ya_metrics-0.0.5.dist-info/LICENSE
djako_plugin_ya_metrics-0.0.5.dist-info/METADATA
djako_plugin_ya_metrics-0.0.5.dist-info/WHEEL
djako_plugin_ya_metrics-0.0.5.dist-info/top_level.txt
djako_plugin_ya_metrics-0.0.5.dist-info/RECORD
