Metadata-Version: 2.1
Name: djako-plugin-ya-metrics
Version: 0.0.5
Summary: Плагин для Djako, который предоставляет интеграцию с API Яндекс метрики и визуализирует счётчики через Chart.js
Home-page: https://github.com/RedHelium?tab=repositories
Author: Brilev Denis
Author-email: brilevdv@digitaleden.ru
Project-URL: Documentation, https://github.com/RedHelium?tab=repositories
Keywords: Djako,Django,CMS,Web,Charts,Yandex Metrics,Admin Widgets
Classifier: Environment :: Web Environment
Classifier: Framework :: Django
Classifier: Framework :: Django :: 5.0
Classifier: Intended Audience :: Developers
Classifier: License :: OSI Approved :: BSD License
Classifier: Operating System :: OS Independent
Classifier: Programming Language :: Python
Classifier: Programming Language :: Python :: 3
Classifier: Programming Language :: Python :: 3 :: Only
Classifier: Programming Language :: Python :: 3.10
Classifier: Programming Language :: Python :: 3.11
Classifier: Programming Language :: Python :: 3.12
Classifier: Topic :: Internet :: WWW/HTTP
Classifier: Topic :: Internet :: WWW/HTTP :: Dynamic Content
Requires-Python: >=3.10
License-File: LICENSE
Requires-Dist: requests >=2.32
Requires-Dist: Django >=5.0
